package cn.search.intepreter.opt;

import cn.search.intepreter.opt.A.Const.aconst_null;
import cn.search.intepreter.opt.A.Load.*;
import cn.search.intepreter.opt.A.Store.*;
import cn.search.intepreter.opt.Array.Load.*;
import cn.search.intepreter.opt.Array.Store.*;
import cn.search.intepreter.opt.B.bipush;
import cn.search.intepreter.opt.Cast.D.d2f;
import cn.search.intepreter.opt.Cast.D.d2i;
import cn.search.intepreter.opt.Cast.D.d2l;
import cn.search.intepreter.opt.Cast.F.f2d;
import cn.search.intepreter.opt.Cast.F.f2i;
import cn.search.intepreter.opt.Cast.F.f2l;
import cn.search.intepreter.opt.Cast.I.*;
import cn.search.intepreter.opt.Cast.L.l2d;
import cn.search.intepreter.opt.Cast.L.l2f;
import cn.search.intepreter.opt.Cast.L.l2i;
import cn.search.intepreter.opt.Compare.D.dcmpg;
import cn.search.intepreter.opt.Compare.D.dcmpl;
import cn.search.intepreter.opt.Compare.F.fcmpg;
import cn.search.intepreter.opt.Compare.F.fcmpl;
import cn.search.intepreter.opt.Compare.I.*;
import cn.search.intepreter.opt.Compare.IF.*;
import cn.search.intepreter.opt.Compare.L.lcmp;
import cn.search.intepreter.opt.Control.*;
import cn.search.intepreter.opt.D.Const.*;
import cn.search.intepreter.opt.D.Load.*;
import cn.search.intepreter.opt.D.Store.*;
import cn.search.intepreter.opt.Extended.*;
import cn.search.intepreter.opt.F.Const.*;
import cn.search.intepreter.opt.F.Load.*;
import cn.search.intepreter.opt.F.Store.*;
import cn.search.intepreter.opt.I.Const.*;
import cn.search.intepreter.opt.I.Load.*;
import cn.search.intepreter.opt.I.Store.*;
import cn.search.intepreter.opt.L.Const.*;
import cn.search.intepreter.opt.L.Dc.*;
import cn.search.intepreter.opt.L.Load.*;
import cn.search.intepreter.opt.L.Store.*;
import cn.search.intepreter.opt.Math.D.*;
import cn.search.intepreter.opt.Math.F.*;
import cn.search.intepreter.opt.Math.I.*;
import cn.search.intepreter.opt.Math.L.*;
import cn.search.intepreter.opt.References.*;
import cn.search.intepreter.opt.S.sipush;
import cn.search.intepreter.opt.Stack.*;

import java.util.HashMap;

public class OpcodeMap {

    static HashMap<Integer, Class<?>> OPCODE = new HashMap<>();

    static {
        OPCODE.put(0, nop.class);
        OPCODE.put(1, aconst_null.class);
        OPCODE.put(2, iconst_m1.class);
        OPCODE.put(3, iconst_0.class);
        OPCODE.put(4, iconst_1.class);
        OPCODE.put(5, iconst_2.class);
        OPCODE.put(6, iconst_3.class);
        OPCODE.put(7, iconst_4.class);
        OPCODE.put(8, iconst_5.class);
        OPCODE.put(9, lconst_0.class);
        OPCODE.put(10, lconst_1.class);
        OPCODE.put(11, fconst_0.class);
        OPCODE.put(12, fconst_1.class);
        OPCODE.put(13, fconst_2.class);
        OPCODE.put(14, dconst_0.class);
        OPCODE.put(15, dconst_1.class);
        OPCODE.put(16, bipush.class);
        OPCODE.put(17, sipush.class);
        OPCODE.put(18, ldc.class);
        OPCODE.put(19, ldc_w.class);
        OPCODE.put(20, ldc2_w.class);
        OPCODE.put(21, iload.class);
        OPCODE.put(22, lload.class);
        OPCODE.put(23, fload.class);
        OPCODE.put(24, dload.class);
        OPCODE.put(25, aload.class);
        OPCODE.put(26, iload_0.class);
        OPCODE.put(27, iload_1.class);
        OPCODE.put(28, iload_2.class);
        OPCODE.put(29, iload_3.class);
        OPCODE.put(30, lload_0.class);
        OPCODE.put(31, lload_1.class);
        OPCODE.put(32, lload_2.class);
        OPCODE.put(33, lload_3.class);
        OPCODE.put(34, fload_0.class);
        OPCODE.put(35, fload_1.class);
        OPCODE.put(36, fload_2.class);
        OPCODE.put(37, fload_3.class);
        OPCODE.put(38, dload_0.class);
        OPCODE.put(39, dload_1.class);
        OPCODE.put(40, dload_2.class);
        OPCODE.put(41, dload_3.class);
        OPCODE.put(42, aload_0.class);
        OPCODE.put(43, aload_1.class);
        OPCODE.put(44, aload_2.class);
        OPCODE.put(45, aload_3.class);
        OPCODE.put(46, iaload.class);
        OPCODE.put(47, laload.class);
        OPCODE.put(48, faload.class);
        OPCODE.put(49, daload.class);
        OPCODE.put(50, aaload.class);
        OPCODE.put(51, baload.class);
        OPCODE.put(52, caload.class);
        OPCODE.put(53, saload.class);
        OPCODE.put(54, istore.class);
        OPCODE.put(55, lstore.class);
        OPCODE.put(56, fstore.class);
        OPCODE.put(57, dstore.class);
        OPCODE.put(58, astore.class);
        OPCODE.put(59, istore_0.class);
        OPCODE.put(60, istore_1.class);
        OPCODE.put(61, istore_2.class);
        OPCODE.put(62, istore_3.class);
        OPCODE.put(63, lstore_0.class);
        OPCODE.put(64, lstore_1.class);
        OPCODE.put(65, lstore_2.class);
        OPCODE.put(66, lstore_3.class);
        OPCODE.put(67, fstore_0.class);
        OPCODE.put(68, fstore_1.class);
        OPCODE.put(69, fstore_2.class);
        OPCODE.put(70, fstore_3.class);
        OPCODE.put(71, dstore_0.class);
        OPCODE.put(72, dstore_1.class);
        OPCODE.put(73, dstore_2.class);
        OPCODE.put(74, dstore_3.class);
        OPCODE.put(75, astore_0.class);
        OPCODE.put(76, astore_1.class);
        OPCODE.put(77, astore_2.class);
        OPCODE.put(78, astore_3.class);
        OPCODE.put(79, iastore.class);
        OPCODE.put(80, lastore.class);
        OPCODE.put(81, fastore.class);
        OPCODE.put(82, dastore.class);
        OPCODE.put(83, aastore.class);
        OPCODE.put(84, bastore.class);
        OPCODE.put(85, castore.class);
        OPCODE.put(86, sastore.class);
        OPCODE.put(87, pop.class);
        OPCODE.put(88, pop2.class);
        OPCODE.put(89, dup.class);
        OPCODE.put(90, dup_x1.class);
        OPCODE.put(91, dup_x2.class);
        OPCODE.put(92, dup2.class);
        OPCODE.put(93, dup2_x1.class);
        OPCODE.put(94, dup2_x2.class);
        OPCODE.put(95, swap.class);
        OPCODE.put(96, iadd.class);
        OPCODE.put(97, ladd.class);
        OPCODE.put(98, fadd.class);
        OPCODE.put(99, dadd.class);
        OPCODE.put(100, isub.class);
        OPCODE.put(101, lsub.class);
        OPCODE.put(102, fsub.class);
        OPCODE.put(103, dsub.class);
        OPCODE.put(104, imul.class);
        OPCODE.put(105, lmul.class);
        OPCODE.put(106, fmul.class);
        OPCODE.put(107, dmul.class);
        OPCODE.put(108, idiv.class);
        OPCODE.put(109, ldiv.class);
        OPCODE.put(110, fdiv.class);
        OPCODE.put(111, ddiv.class);
        OPCODE.put(112, irem.class);
        OPCODE.put(113, lrem.class);
        OPCODE.put(114, frem.class);
        OPCODE.put(115, drem.class);
        OPCODE.put(116, ineg.class);
        OPCODE.put(117, lneg.class);
        OPCODE.put(118, fneg.class);
        OPCODE.put(119, dneg.class);
        OPCODE.put(120, ishl.class);
        OPCODE.put(121, lshl.class);
        OPCODE.put(122, ishr.class);
        OPCODE.put(123, lshr.class);
        OPCODE.put(124, iushr.class);
        OPCODE.put(125, lushr.class);
        OPCODE.put(126, iand.class);
        OPCODE.put(127, land.class);
        OPCODE.put(128, ior.class);
        OPCODE.put(129, lor.class);
        OPCODE.put(130, ixor.class);
        OPCODE.put(131, lxor.class);
        OPCODE.put(132, iinc.class);
        OPCODE.put(133, i2l.class);
        OPCODE.put(134, i2f.class);
        OPCODE.put(135, i2d.class);
        OPCODE.put(136, l2i.class);
        OPCODE.put(137, l2f.class);
        OPCODE.put(138, l2d.class);
        OPCODE.put(139, f2i.class);
        OPCODE.put(140, f2l.class);
        OPCODE.put(141, f2d.class);
        OPCODE.put(142, d2i.class);
        OPCODE.put(143, d2l.class);
        OPCODE.put(144, d2f.class);
        OPCODE.put(145, i2b.class);
        OPCODE.put(146, i2c.class);
        OPCODE.put(147, i2s.class);
        OPCODE.put(148, lcmp.class);
        OPCODE.put(149, fcmpl.class);
        OPCODE.put(150, fcmpg.class);
        OPCODE.put(151, dcmpl.class);
        OPCODE.put(152, dcmpg.class);
        OPCODE.put(153, ifeq.class);
        OPCODE.put(154, ifne.class);
        OPCODE.put(155, iflt.class);
        OPCODE.put(156, ifge.class);
        OPCODE.put(157, ifgt.class);
        OPCODE.put(158, ifle.class);
        OPCODE.put(159, if_icmpeq.class);
        OPCODE.put(160, if_icmpne.class);
        OPCODE.put(161, if_icmplt.class);
        OPCODE.put(162, if_icmpge.class);
        OPCODE.put(163, if_icmpgt.class);
        OPCODE.put(164, if_icmple.class);
        OPCODE.put(165, if_acmpeq.class);
        OPCODE.put(166, if_acmpne.class);
        OPCODE.put(167, _goto.class);
        OPCODE.put(168, jsr.class);
        OPCODE.put(169, ret.class);
        OPCODE.put(170, tableswitch.class);
        OPCODE.put(171, lookupswitch.class);
        OPCODE.put(172, ireturn.class);
        OPCODE.put(173, lreturn.class);
        OPCODE.put(174, freturn.class);
        OPCODE.put(175, dreturn.class);
        OPCODE.put(176, areturn.class);
        OPCODE.put(177, _return.class);
        OPCODE.put(178, getstatic.class);
        OPCODE.put(179, putstatic.class);
        OPCODE.put(180, getfield.class);
        OPCODE.put(181, putfield.class);
        OPCODE.put(182, invokevirtual.class);
        OPCODE.put(183, invokespecial.class);
        OPCODE.put(184, invokestatic.class);
        OPCODE.put(185, invokeinterface.class);
        OPCODE.put(186, invokedynamic.class);
        OPCODE.put(187, _new.class);
        OPCODE.put(188, newarray.class);
        OPCODE.put(189, anewarray.class);
        OPCODE.put(190, arraylength.class);
        OPCODE.put(191, athrow.class);
        OPCODE.put(192, checkcast.class);
        OPCODE.put(193, _instanceof.class);
        OPCODE.put(194, monitorenter.class);
        OPCODE.put(195, monitorexit.class);
        OPCODE.put(196, wide.class);
        OPCODE.put(197, multianewarray.class);
        OPCODE.put(198, ifnull.class);
        OPCODE.put(199, ifnonnull.class);
        OPCODE.put(200, goto_w.class);
        OPCODE.put(201, jsr_w.class);
    }

}
